{
  "version": 1,
  "default_view": "all",
  "view_order": [
    "all"
  ],
  "views": {
    "all": {
      "id": "all",
      "label": "All",
      "split_names": [
        "data"
      ],
      "summary": {
        "num_images": 7237,
        "num_annotations": 67472,
        "num_images_with_annotations": 7237,
        "num_images_without_annotations": 0,
        "num_classes": 11,
        "annotation_coverage": 1.0,
        "class_distribution": {
          "Reflective Crack": 12428,
          "Lane Longitudinal Crack": 12102,
          "Transvers Crack": 5343,
          "Sealed Reflective Crack": 5910,
          "Aligator Crack": 4838,
          "pothole": 637,
          "Block Crack": 9709,
          "Longitudinal Crack": 2892,
          "Sealed Longitudinal Crack": 13610,
          "Sealed Transvers Cracks": 1,
          "Sealed Block Crack": 2
        }
      },
      "artifacts": {
        "class_balance": {
          "columns": [
            "Class",
            "Images",
            "Objects",
            "Count on image, average",
            "Area on image, average (%)"
          ],
          "data": [
            [
              "Sealed Longitudinal Crack",
              3022,
              13610,
              4.5036,
              6.1754
            ],
            [
              "Reflective Crack",
              4211,
              12428,
              2.9513,
              7.7419
            ],
            [
              "Lane Longitudinal Crack",
              4197,
              12102,
              2.8835,
              6.0558
            ],
            [
              "Block Crack",
              3214,
              9709,
              3.0208,
              15.8468
            ],
            [
              "Sealed Reflective Crack",
              1856,
              5910,
              3.1843,
              7.1499
            ],
            [
              "Transvers Crack",
              2222,
              5343,
              2.4046,
              3.4087
            ],
            [
              "Aligator Crack",
              1344,
              4838,
              3.5997,
              8.7891
            ],
            [
              "Longitudinal Crack",
              1457,
              2892,
              1.9849,
              4.6988
            ],
            [
              "pothole",
              228,
              637,
              2.7939,
              6.1077
            ],
            [
              "Sealed Block Crack",
              1,
              2,
              2.0,
              7.5891
            ],
            [
              "Sealed Transvers Cracks",
              1,
              1,
              1.0,
              0.9629
            ]
          ],
          "description": "Images column counts images containing at least one object of class.",
          "options": {
            "sort": {
              "columnIndex": 2,
              "order": "desc"
            },
            "pageSize": 100
          }
        },
        "class_cooccurrence": {
          "type": "matrix",
          "labels": [
            "Aligator Crack",
            "Block Crack",
            "Lane Longitudinal Crack",
            "Longitudinal Crack",
            "Reflective Crack",
            "Sealed Block Crack",
            "Sealed Longitudinal Crack",
            "Sealed Reflective Crack",
            "Sealed Transvers Cracks",
            "Transvers Crack",
            "pothole"
          ],
          "data": [
            [
              1344,
              817,
              1239,
              243,
              604,
              0,
              229,
              48,
              0,
              649,
              214
            ],
            [
              817,
              3214,
              2184,
              744,
              1554,
              0,
              1114,
              648,
              1,
              1650,
              15
            ],
            [
              1239,
              2184,
              4197,
              692,
              2518,
              0,
              881,
              319,
              0,
              1901,
              220
            ],
            [
              243,
              744,
              692,
              1457,
              934,
              0,
              669,
              537,
              1,
              430,
              43
            ],
            [
              604,
              1554,
              2518,
              934,
              4211,
              0,
              1804,
              727,
              0,
              1137,
              6
            ],
            [
              0,
              0,
              0,
              0,
              0,
              1,
              1,
              1,
              0,
              0,
              0
            ],
            [
              229,
              1114,
              881,
              669,
              1804,
              1,
              3022,
              1546,
              1,
              407,
              7
            ],
            [
              48,
              648,
              319,
              537,
              727,
              1,
              1546,
              1856,
              1,
              226,
              4
            ],
            [
              0,
              1,
              0,
              1,
              0,
              0,
              1,
              1,
              1,
              0,
              0
            ],
            [
              649,
              1650,
              1901,
              430,
              1137,
              0,
              407,
              226,
              0,
              2222,
              9
            ],
            [
              214,
              15,
              220,
              43,
              6,
              0,
              7,
              4,
              0,
              9,
              228
            ]
          ],
          "title": "Co-occurrence Matrix",
          "description": "Cell [i,j] is number of images that contain both classes i and j."
        },
        "class_sizes": {
          "columns": [
            "Class",
            "Object count",
            "Avg area (%)",
            "Max area (%)",
            "Min area (%)",
            "Min height (px)",
            "Min height (%)",
            "Max height (px)",
            "Max height (%)",
            "Avg height (px)",
            "Avg height (%)"
          ],
          "data": [
            [
              "Sealed Longitudinal Crack",
              13610,
              1.3712,
              37.0757,
              0.0562,
              14.0,
              2.1875,
              447.0,
              69.8438,
              103.76,
              16.2202
            ],
            [
              "Reflective Crack",
              12428,
              2.6232,
              33.9844,
              0.0168,
              5.0,
              0.7812,
              400.0,
              62.5,
              51.58,
              8.0622
            ],
            [
              "Lane Longitudinal Crack",
              12102,
              2.1001,
              13.6663,
              0.0857,
              9.0,
              1.4062,
              579.0,
              90.4688,
              149.5,
              23.3593
            ],
            [
              "Block Crack",
              9709,
              5.2458,
              35.3438,
              0.2656,
              19.0,
              2.9688,
              507.0,
              79.2188,
              153.81,
              24.0326
            ],
            [
              "Sealed Reflective Crack",
              5910,
              2.2454,
              26.9407,
              0.0667,
              7.0,
              1.0938,
              244.0,
              38.125,
              49.64,
              7.757
            ],
            [
              "Transvers Crack",
              5343,
              1.4176,
              18.3779,
              0.0254,
              4.0,
              0.625,
              164.0,
              25.625,
              48.8,
              7.6246
            ],
            [
              "Aligator Crack",
              4838,
              2.4416,
              17.5635,
              0.1709,
              18.0,
              2.8125,
              417.0,
              65.1562,
              113.32,
              17.706
            ],
            [
              "Longitudinal Crack",
              2892,
              2.3673,
              14.209,
              0.1011,
              23.0,
              3.5937,
              612.0,
              95.625,
              160.19,
              25.0291
            ],
            [
              "pothole",
              637,
              2.1861,
              8.563,
              0.2512,
              19.0,
              2.9688,
              247.0,
              38.5938,
              89.44,
              13.9749
            ],
            [
              "Sealed Block Crack",
              2,
              3.7946,
              4.0403,
              3.5488,
              67.0,
              10.4688,
              92.0,
              14.375,
              79.5,
              12.4219
            ],
            [
              "Sealed Transvers Cracks",
              1,
              0.9629,
              0.9629,
              0.9629,
              34.0,
              5.3125,
              34.0,
              5.3125,
              34.0,
              5.3125
            ]
          ],
          "description": "Area and height are relative to image size where (%) columns are 0-100 scale."
        },
        "objects_distribution": {
          "type": "heatmap",
          "title": "Objects on images - distribution for every class",
          "x_labels": [
            "0",
            "1",
            "2",
            "3",
            "4",
            "5",
            "6",
            "7",
            "8",
            "9",
            "10",
            "11",
            "12",
            "13",
            "14",
            "15",
            "16"
          ],
          "y_labels": [
            "Sealed Longitudinal Crack",
            "Reflective Crack",
            "Lane Longitudinal Crack",
            "Block Crack",
            "Sealed Reflective Crack",
            "Transvers Crack",
            "Aligator Crack",
            "Longitudinal Crack",
            "pothole",
            "Sealed Block Crack",
            "Sealed Transvers Cracks"
          ],
          "z": [
            [
              4215,
              308,
              465,
              573,
              479,
              305,
              240,
              208,
              135,
              108,
              85,
              40,
              41,
              13,
              18,
              3,
              1
            ],
            [
              3026,
              1059,
              978,
              833,
              622,
              306,
              199,
              110,
              58,
              17,
              14,
              8,
              4,
              3,
              0,
              0,
              0
            ],
            [
              3040,
              624,
              1298,
              1226,
              484,
              290,
              173,
              64,
              27,
              3,
              3,
              2,
              2,
              1,
              0,
              0,
              0
            ],
            [
              4023,
              745,
              789,
              618,
              424,
              270,
              192,
              107,
              42,
              22,
              4,
              1,
              0,
              0,
              0,
              0,
              0
            ],
            [
              5381,
              388,
              444,
              346,
              283,
              147,
              109,
              75,
              34,
              24,
              4,
              2,
              0,
              0,
              0,
              0,
              0
            ],
            [
              5015,
              768,
              537,
              445,
              282,
              133,
              33,
              19,
              3,
              2,
              0,
              0,
              0,
              0,
              0,
              0,
              0
            ],
            [
              5893,
              233,
              279,
              335,
              150,
              85,
              48,
              68,
              90,
              36,
              13,
              5,
              2,
              0,
              0,
              0,
              0
            ],
            [
              5780,
              668,
              418,
              213,
              94,
              27,
              27,
              6,
              2,
              2,
              0,
              0,
              0,
              0,
              0,
              0,
              0
            ],
            [
              7009,
              70,
              49,
              39,
              30,
              22,
              8,
              7,
              2,
              1,
              0,
              0,
              0,
              0,
              0,
              0,
              0
            ],
            [
              7236,
              0,
              1,
              0,
              0,
              0,
              0,
              0,
              0,
              0,
              0,
              0,
              0,
              0,
              0,
              0,
              0
            ],
            [
              7236,
              1,
              0,
              0,
              0,
              0,
              0,
              0,
              0,
              0,
              0,
              0,
              0,
              0,
              0,
              0,
              0
            ]
          ],
          "description": "Value = number of images where class has exactly x objects."
        },
        "classes_per_image": {
          "type": "histogram",
          "title": "Distinct classes per image",
          "series": [
            {
              "name": "classes",
              "data": [
                {
                  "x": "0",
                  "y": 0
                },
                {
                  "x": "1",
                  "y": 567
                },
                {
                  "x": "2",
                  "y": 2296
                },
                {
                  "x": "3",
                  "y": 1896
                },
                {
                  "x": "4",
                  "y": 1623
                },
                {
                  "x": "5",
                  "y": 724
                },
                {
                  "x": "6",
                  "y": 123
                },
                {
                  "x": "7",
                  "y": 8
                }
              ]
            }
          ]
        },
        "classes_treemap": {
          "type": "treemap",
          "title": "Average area of class objects on image",
          "series": [
            {
              "data": [
                {
                  "x": "Sealed Longitudinal Crack",
                  "y": 6.1754
                },
                {
                  "x": "Reflective Crack",
                  "y": 7.7419
                },
                {
                  "x": "Lane Longitudinal Crack",
                  "y": 6.0558
                },
                {
                  "x": "Block Crack",
                  "y": 15.8468
                },
                {
                  "x": "Sealed Reflective Crack",
                  "y": 7.1499
                },
                {
                  "x": "Transvers Crack",
                  "y": 3.4087
                },
                {
                  "x": "Aligator Crack",
                  "y": 8.7891
                },
                {
                  "x": "Longitudinal Crack",
                  "y": 4.6988
                },
                {
                  "x": "pothole",
                  "y": 6.1077
                },
                {
                  "x": "Sealed Block Crack",
                  "y": 7.5891
                },
                {
                  "x": "Sealed Transvers Cracks",
                  "y": 0.9629
                }
              ]
            }
          ],
          "value_unit": "%"
        }
      },
      "samples_summary": {
        "sample_count": 10,
        "slider_pairs": 10,
        "samples_dir": "visualizations/samples",
        "samples_manifest": "visualizations/samples/samples_manifest.json",
        "annotated_samples_dir": "visualizations/samples/annotated",
        "sample_annotations_dir": "visualizations/samples/annotations"
      },
      "spatial_heatmaps": {
        "generated": true,
        "dir": "visualizations/spatial_heatmaps",
        "classes": [
          {
            "class": "Sealed Longitudinal Crack",
            "file": "visualizations/spatial_heatmaps/Sealed_Longitudinal_Crack.png"
          },
          {
            "class": "Reflective Crack",
            "file": "visualizations/spatial_heatmaps/Reflective_Crack.png"
          },
          {
            "class": "Lane Longitudinal Crack",
            "file": "visualizations/spatial_heatmaps/Lane_Longitudinal_Crack.png"
          },
          {
            "class": "Block Crack",
            "file": "visualizations/spatial_heatmaps/Block_Crack.png"
          },
          {
            "class": "Sealed Reflective Crack",
            "file": "visualizations/spatial_heatmaps/Sealed_Reflective_Crack.png"
          },
          {
            "class": "Transvers Crack",
            "file": "visualizations/spatial_heatmaps/Transvers_Crack.png"
          },
          {
            "class": "Aligator Crack",
            "file": "visualizations/spatial_heatmaps/Aligator_Crack.png"
          },
          {
            "class": "Longitudinal Crack",
            "file": "visualizations/spatial_heatmaps/Longitudinal_Crack.png"
          },
          {
            "class": "pothole",
            "file": "visualizations/spatial_heatmaps/pothole.png"
          },
          {
            "class": "Sealed Block Crack",
            "file": "visualizations/spatial_heatmaps/Sealed_Block_Crack.png"
          },
          {
            "class": "Sealed Transvers Cracks",
            "file": "visualizations/spatial_heatmaps/Sealed_Transvers_Cracks.png"
          }
        ]
      }
    }
  }
}